django_github_tags/__init__.py
django_github_tags/errors.py
django_github_tags/helper.py
django_github_tags/templatetags/__init__.py
django_github_tags/templatetags/django_github_tags.py
django_github_tags-1.0.0.dist-info/LICENSE
django_github_tags-1.0.0.dist-info/WHEEL
django_github_tags-1.0.0.dist-info/METADATA
django_github_tags-1.0.0.dist-info/RECORD
