Metadata-Version: 2.1
Name: django-github-tags
Version: 1.0.0
Summary: Access to GitHub API using tags in your Django templates.
License: GPL-3.0 License
Author: PabloLec
Author-email: pablo.lecolinet@gmail.com
Requires-Python: >=3.6,<4.0
Classifier: License :: Other/Proprietary License
Classifier: Programming Language :: Python :: 3
Classifier: Programming Language :: Python :: 3.6
Classifier: Programming Language :: Python :: 3.7
Classifier: Programming Language :: Python :: 3.8
Classifier: Programming Language :: Python :: 3.9
Requires-Dist: requests (>=2.25.1,<3.0.0)
